lorem_ipsum/__init__.py
lorem_ipsum/lorem_generator.py
lorem_aoponto-0.1.0.dist-info/entry_points.txt
lorem_aoponto-0.1.0.dist-info/METADATA
lorem_aoponto-0.1.0.dist-info/WHEEL
lorem_aoponto-0.1.0.dist-info/RECORD
